README.md
setup.cfg
setup.py
steppy_toolkit.egg-info/PKG-INFO
steppy_toolkit.egg-info/SOURCES.txt
steppy_toolkit.egg-info/dependency_links.txt
steppy_toolkit.egg-info/not-zip-safe
steppy_toolkit.egg-info/requires.txt
steppy_toolkit.egg-info/top_level.txt
toolkit/__init__.py
toolkit/postprocessing.py
toolkit/toolkit_base.py
toolkit/utils.py
toolkit/catboost_transformers/__init__.py
toolkit/catboost_transformers/models.py
toolkit/keras_transformers/__init__.py
toolkit/keras_transformers/architectures.py
toolkit/keras_transformers/callbacks.py
toolkit/keras_transformers/contrib.py
toolkit/keras_transformers/embeddings.py
toolkit/keras_transformers/loaders.py
toolkit/keras_transformers/models.py
toolkit/lightgbm_transformers/__init__.py
toolkit/lightgbm_transformers/models.py
toolkit/preprocessing/__init__.py
toolkit/preprocessing/misc.py
toolkit/preprocessing/text.py
toolkit/pytorch_transformers/__init__.py
toolkit/pytorch_transformers/callbacks.py
toolkit/pytorch_transformers/models.py
toolkit/pytorch_transformers/utils.py
toolkit/pytorch_transformers/validation.py
toolkit/pytorch_transformers/architectures/__init__.py
toolkit/pytorch_transformers/architectures/unet.py
toolkit/pytorch_transformers/architectures/utils.py
toolkit/pytorch_transformers/loaders/__init__.py
toolkit/pytorch_transformers/loaders/classification.py
toolkit/pytorch_transformers/loaders/segmentation.py
toolkit/sklearn_transformers/__init__.py
toolkit/sklearn_transformers/models.py
toolkit/xgboost_transformers/__init__.py
toolkit/xgboost_transformers/models.py