Metadata-Version: 1.1
Name: steppy-toolkit
Version: 0.1.13
Summary: Set of tools to make your work with steppy faster and more effective.
Home-page: https://github.com/minerva-ml/steppy-toolkit
Author: Kamil A. Kaczmarek, Jakub Czakon
Author-email: kamil.kaczmarek@neptune.ml, jakub.czakon@neptune.ml
License: MIT
Download-URL: https://github.com/minerva-ml/steppy-toolkit/archive/0.1.13.tar.gz
Keywords: machine-learning,reproducibility,pipeline,tools
Platform: UNKNOWN
